{
  "experiment_code": "E001",
  "variant_code": null,
  "slot_id": "tyo13",
  "side": "buy",
  "baseline": {
    "entry_clock_local": "13:40",
    "forced_exit_clock_local": "14:35",
    "tp_pips": 20,
    "sl_pips": 15,
    "filter_labels": ["trend_ge_0_5"]
  },
  "comparison_family": "trend_ratio",
  "comparison_labels": ["all", "trend_ge_0_4", "trend_ge_0_5", "trend_ge_0_6", "trend_ge_0_7"],
  "pass_stability_gate": true,
  "notes": "tyo13 buy redo. Previous 13:00 buy/ge0 is treated as an extension of the 12:55 buy edge and is intentionally avoided. Use 13:40 trend_ratio trend_ge_0_5 as a distinct later candidate. all is retained only as a reference, not as an adoption candidate."
}
